web_traffic_monitor/Client.py
web_traffic_monitor/__init__.py
web_traffic_monitor/__main__.py
web_traffic_monitor/engines/__init__.py
web_traffic_monitor/engines/base.py
web_traffic_monitor/engines/sqlite3.py
web_traffic_monitor/schemas/__init__.py
web_traffic_monitor/schemas/base.py
web_traffic_monitor/schemas/test.py
web_traffic_monitor-0.3.0.dist-info/LICENSE
web_traffic_monitor-0.3.0.dist-info/METADATA
web_traffic_monitor-0.3.0.dist-info/WHEEL
web_traffic_monitor-0.3.0.dist-info/top_level.txt
web_traffic_monitor-0.3.0.dist-info/RECORD
