Metadata-Version: 2.1
Name: web_traffic_monitor
Version: 0.3.0
Summary: Basic system for tracking website visits and redirecting urls
Home-page: https://pypi.org/project/web-traffic-monitor/
Author: James Kabbes
Project-URL: GitHub, https://github.com/jameskabbes/web_traffic_monitor
Project-URL: Documentation, https://jameskabbes.github.io/web_traffic_monitor
Classifier: Programming Language :: Python :: 3
Classifier: License :: OSI Approved :: MIT License
Classifier: Operating System :: OS Independent
Requires-Python: >=3.7
License-File: LICENSE
